{
    "created_time": "2018-09-09T16:02:53Z",
    "files": [
        {
            "attachment_folder": "",
            "attachments": [
            ],
            "created_time": "2018-09-09T16:03:07Z",
            "modified_time": "2018-09-11T09:28:57Z",
            "name": "PPT教程.md",
            "tags": [
            ]
        },
        {
            "attachment_folder": "",
            "attachments": [
            ],
            "created_time": "2018-09-09T16:25:32Z",
            "modified_time": "2018-09-09T16:25:32Z",
            "name": "微信资料备份.md",
            "tags": [
            ]
        }
    ],
    "sub_directories": [
    ],
    "version": "1"
}
